[{"type": "business", "longitude": -73.8418139, "full_address": "2 Rue Blainville O\nSainte-Therese, QC J7E 1W9", "rest_id": 9378, "categories": ["French", "Restaurants"], "state": "QC", "open": true, "business_id": "rcLN9LQvfYl0vuayNKIHPQ", "neighborhoods": [], "review_count": 4, "attributes": {"Good For Groups": true, "Take-out": true, "Good for Kids": true, "Delivery": false, "Takes Reservations": true}, "hours": {}, "latitude": 45.6395901, "city": "Sainte-Therese", "name": "Restaurant Arousse (Le)", "stars": 5.0}]