[{"type": "business", "longitude": -73.6793369, "full_address": "834 Blvd D\u00e9carie\nSt-Laurent, QC H4L 3L9", "rest_id": 16251, "categories": ["Cafes", "Restaurants"], "state": "QC", "open": false, "business_id": "_w0x4_OmXuKaWPRGD4q-JA", "neighborhoods": [], "review_count": 3, "attributes": {"Ambience": {"classy": false, "trendy": false, "romantic": false, "casual": false, "upscale": false, "touristy": false, "hipster": false, "intimate": false}, "Alcohol": "none", "Price Range": 1, "Good For": {"brunch": false, "dessert": false, "latenight": false, "breakfast": false, "lunch": false, "dinner": false}, "Attire": "casual", "Accepts Credit Cards": true, "Good for Kids": true, "Parking": {"validated": false, "valet": false, "garage": false, "street": false, "lot": false}, "Delivery": false, "Waiter Service": false, "Wi-Fi": "free", "Caters": false, "Takes Reservations": false, "Has TV": true, "Good For Groups": true, "Take-out": true, "Outdoor Seating": true, "Noise Level": "quiet"}, "hours": {}, "latitude": 45.5120624, "city": "St-Laurent", "name": "Tache de Caf\u00e9", "stars": 4.5}]