[{"type": "business", "longitude": -89.20037, "full_address": "224 W Cottage Grove Rd\nCottage Grove, WI 53527", "rest_id": 3201, "categories": ["Pizza", "Restaurants"], "state": "WI", "open": true, "business_id": "gsb1ZXNd36YwANID3u1M-g", "neighborhoods": [], "review_count": 7, "attributes": {"Accepts Credit Cards": true, "Price Range": 2, "Takes Reservations": false, "Has TV": true, "Attire": "casual", "Outdoor Seating": true, "Good For Groups": true, "Take-out": true, "Good for Kids": true, "Delivery": true, "Parking": {"validated": false, "valet": false, "garage": false, "street": false, "lot": false}}, "hours": {"Sunday": {"open": "12:00", "close": "21:00"}, "Tuesday": {"open": "11:00", "close": "21:00"}, "Monday": {"open": "11:00", "close": "21:00"}, "Saturday": {"open": "11:00", "close": "23:00"}, "Friday": {"open": "11:00", "close": "23:00"}, "Wednesday": {"open": "11:00", "close": "21:00"}, "Thursday": {"open": "11:00", "close": "21:00"}}, "latitude": 43.086476, "city": "Cottage Grove", "name": "Papa Jimmy's Pizzeria", "stars": 3.0}, {"type": "business", "longitude": -89.206333, "full_address": "320 W Cottage Grove Rd\nCottage Grove, WI 53527", "rest_id": 3202, "categories": ["Restaurants"], "state": "WI", "open": true, "business_id": "d24w8_TEu1QamA3qFI5JMw", "neighborhoods": [], "review_count": 9, "attributes": {"Ambience": {"classy": false, "trendy": false, "romantic": false, "divey": false, "casual": false, "upscale": false, "touristy": false, "hipster": false, "intimate": false}, "Alcohol": "full_bar", "Price Range": 2, "Good For": {"dessert": false, "brunch": true, "latenight": false, "breakfast": false, "lunch": false, "dinner": false}, "Attire": "casual", "Good for Kids": false, "Parking": {"validated": false, "valet": false, "garage": false, "street": false, "lot": false}, "Delivery": false, "Waiter Service": true, "Wi-Fi": "no", "Caters": false, "Takes Reservations": false, "Has TV": true, "Good For Groups": true, "Take-out": true, "Accepts Credit Cards": true, "Noise Level": "average"}, "hours": {}, "latitude": 43.086641, "city": "Cottage Grove", "name": "Black Bear Inn", "stars": 2.5}, {"type": "business", "longitude": -89.202522, "full_address": "214 W Cottage Grove Rd\nCottage Grove, WI 53527", "rest_id": 13160, "categories": ["Breakfast & Brunch", "Restaurants"], "state": "WI", "open": true, "business_id": "tUMGHqf05yRUsBuTAoVToA", "neighborhoods": [], "review_count": 7, "attributes": {"Alcohol": "none", "Price Range": 1, "Good For": {"brunch": false, "dessert": false, "latenight": false, "breakfast": false, "lunch": false, "dinner": false}, "Attire": "casual", "Accepts Credit Cards": true, "Good for Kids": true, "Wheelchair Accessible": true, "Delivery": false, "Waiter Service": false, "Wi-Fi": "free", "Parking": {"validated": false, "valet": false, "garage": false, "street": false, "lot": false}, "Takes Reservations": true, "Has TV": false, "Good For Groups": true, "Outdoor Seating": false, "Noise Level": "average"}, "hours": {}, "latitude": 43.086368, "city": "Cottage Grove", "name": "Village Cafe", "stars": 4.0}, {"type": "business", "longitude": -89.209226, "full_address": "401 W Cottage Grove Rd\nCottage Grove, WI 53527", "rest_id": 17680, "categories": ["Burgers", "Fast Food", "Restaurants"], "state": "WI", "open": true, "business_id": "-3fmY6IhikhUQXpiaLgxHA", "neighborhoods": [], "review_count": 3, "attributes": {"Attire": "casual", "Noise Level": "loud", "Delivery": false}, "hours": {"Sunday": {"open": "05:00", "close": "23:00"}, "Tuesday": {"open": "05:00", "close": "23:00"}, "Monday": {"open": "05:00", "close": "23:00"}, "Saturday": {"open": "05:00", "close": "23:00"}, "Friday": {"open": "05:00", "close": "23:00"}, "Wednesday": {"open": "05:00", "close": "23:00"}, "Thursday": {"open": "05:00", "close": "23:00"}}, "latitude": 43.087207, "city": "Cottage Grove", "name": "McDonald's", "stars": 1.5}, {"type": "business", "longitude": -89.1992292, "full_address": "4691 County Hwy N\nCottage Grove, WI 53527", "rest_id": 18744, "categories": ["Cafes", "Restaurants"], "state": "WI", "open": true, "business_id": "eKT11QqlcEJUuq-OsaPMtw", "neighborhoods": [], "review_count": 10, "attributes": {"Ambience": {"classy": false, "trendy": false, "romantic": false, "divey": false, "casual": false, "upscale": false, "touristy": false, "hipster": false, "intimate": false}, "Alcohol": "none", "Price Range": 1, "Good For": {"dessert": false, "brunch": false, "latenight": false, "breakfast": false, "lunch": false, "dinner": false}, "Attire": "casual", "Outdoor Seating": true, "Good for Kids": true, "Wheelchair Accessible": true, "Parking": {"validated": false, "valet": false, "garage": false, "street": false, "lot": true}, "Delivery": true, "Waiter Service": false, "Wi-Fi": "free", "Caters": true, "Takes Reservations": false, "Has TV": false, "Good For Groups": true, "Take-out": true, "Accepts Credit Cards": true, "Noise Level": "average"}, "hours": {"Sunday": {"open": "08:00", "close": "15:30"}, "Tuesday": {"open": "06:00", "close": "15:30"}, "Monday": {"open": "06:00", "close": "15:30"}, "Saturday": {"open": "07:00", "close": "20:00"}, "Friday": {"open": "06:00", "close": "20:00"}, "Wednesday": {"open": "06:00", "close": "15:30"}, "Thursday": {"open": "06:00", "close": "15:30"}}, "latitude": 43.1048724, "city": "Cottage Grove", "name": "School Grounds Cafe", "stars": 5.0}]