[{"type": "business", "longitude": 8.5057262, "full_address": "Ettlinger Str.  1\n76307 Karlsbad", "rest_id": 13809, "categories": ["German", "Baden", "Bed & Breakfast", "Event Planning & Services", "Hotels & Travel", "Hotels", "Restaurants"], "state": "BW", "open": true, "business_id": "yzujxM_HrrNB3dri5SX18Q", "neighborhoods": [], "review_count": 5, "attributes": {"Alcohol": "beer_and_wine", "Price Range": 2, "Good For": {"dessert": false, "brunch": false, "latenight": false, "breakfast": false, "lunch": false, "dinner": false}, "Attire": "casual", "Outdoor Seating": true, "Wheelchair Accessible": false, "Parking": {"garage": false, "valet": false, "validated": false, "street": false, "lot": false}, "Delivery": false, "Waiter Service": true, "Wi-Fi": "no", "Smoking": "yes", "Dogs Allowed": false, "Takes Reservations": true, "Good For Groups": true, "Take-out": false, "Accepts Credit Cards": false, "Noise Level": "average"}, "hours": {"Sunday": {"open": "11:30", "close": "23:00"}, "Tuesday": {"open": "11:30", "close": "23:00"}, "Monday": {"open": "11:30", "close": "23:00"}, "Saturday": {"open": "11:30", "close": "23:00"}, "Friday": {"open": "11:30", "close": "23:00"}, "Wednesday": {"open": "11:30", "close": "23:00"}, "Thursday": {"open": "11:30", "close": "23:00"}}, "latitude": 48.9168511, "city": "Karlsbad", "name": "Gr\u00fcner Baum", "stars": 4.0}, {"type": "business", "longitude": 8.5031, "full_address": "Benzstr. 5\n76307 Karlsbad", "rest_id": 13903, "categories": ["Food", "Coffee & Tea", "Cafes", "Restaurants"], "state": "BW", "open": true, "business_id": "EpZsI6uHsyaE1xHI-7Qglw", "neighborhoods": [], "review_count": 9, "attributes": {"Alcohol": "full_bar", "Price Range": 3, "Attire": "casual", "Good for Kids": true, "Delivery": true, "Accepts Credit Cards": true, "Smoking": "yes", "Parking": {"garage": false, "valet": false, "validated": false, "street": false, "lot": false}, "Takes Reservations": true, "Has TV": true, "Good For Groups": true, "Take-out": true, "Outdoor Seating": true}, "hours": {}, "latitude": 48.9202, "city": "Karlsbad", "name": "Triangel Gastst\u00e4ttenbetriebs GmbH", "stars": 3.5}]